ambrozia/VERSION
ambrozia/__init__.py
ambrozia/designer/__init__.py
ambrozia/designer/designer.py
ambrozia/designer/handlers.py
ambrozia/preprocessing/__init__.py
ambrozia/preprocessing/aggregate.py
ambrozia/preprocessing/cuped.py
ambrozia/preprocessing/ml_var_reducer.py
ambrozia/preprocessing/preprocessor.py
ambrozia/preprocessing/robust.py
ambrozia/spark_tools/__init__.py
ambrozia/spark_tools/empiric.py
ambrozia/spark_tools/split_tools.py
ambrozia/spark_tools/stat_criteria.py
ambrozia/spark_tools/stratification.py
ambrozia/spark_tools/theory.py
ambrozia/splitter/__init__.py
ambrozia/splitter/handlers.py
ambrozia/splitter/splitter.py
ambrozia/tester/__init__.py
ambrozia/tester/binary_result_evaluation.py
ambrozia/tester/tester.py
ambrozia/tools/__init__.py
ambrozia/tools/_lib/__init__.py
ambrozia/tools/_lib/_bin_ci_aide.py
ambrozia/tools/_lib/_bootstrap_tools.py
ambrozia/tools/_lib/_selection_aide.py
ambrozia/tools/_lib/_tools_aide.py
ambrozia/tools/ab_abstract_component.py
ambrozia/tools/back_tools.py
ambrozia/tools/bin_intervals.py
ambrozia/tools/empirical_tools.py
ambrozia/tools/knn.py
ambrozia/tools/log.py
ambrozia/tools/pvalue_tools.py
ambrozia/tools/split_tools.py
ambrozia/tools/stat_criteria.py
ambrozia/tools/stratification.py
ambrozia/tools/theoretical_tools.py
ambrozia/tools/tools.py
ambrozia/tools/type_checks.py
ambrozia/types.py
ambrozia/version.py
ambrozia-0.1.2.dist-info/LICENSE
ambrozia-0.1.2.dist-info/WHEEL
ambrozia-0.1.2.dist-info/METADATA
ambrozia-0.1.2.dist-info/RECORD
