Metadata-Version: 2.1
Name: ambrozia
Version: 0.1.2
Summary: A Python library for working with A/B tests.
Home-page: https://github.com/MobileTeleSystems/Ambrosia
License: Apache-2.0
Keywords: ambrosia,ab testing,split testing,experiment design,groups split
Author: Aslan Bayramkulov
Author-email: aslan.bayramkulov96@gmail.com
Requires-Python: >=3.7.2,<3.10.4
Classifier: Development Status :: 3 - Alpha
Classifier: Intended Audience :: Education
Classifier: Intended Audience :: Science/Research
Classifier: License :: OSI Approved :: Apache Software License
Classifier: Operating System :: MacOS
Classifier: Operating System :: Microsoft :: Windows
Classifier: Operating System :: Unix
Classifier: Programming Language :: Python :: 3
Classifier: Programming Language :: Python :: 3.10
Classifier: Programming Language :: Python :: 3.7
Classifier: Programming Language :: Python :: 3.8
Classifier: Programming Language :: Python :: 3.9
Classifier: Topic :: Scientific/Engineering :: Mathematics
Classifier: Topic :: Software Development :: Libraries :: Python Modules
Requires-Dist: PyYAML (==6.0)
Requires-Dist: catboost (>=1.0.4,<2.0.0)
Requires-Dist: hyperopt (>=0.2.7,<0.3.0)
Requires-Dist: jinja2 (>=3.0.0,<4.0.0)
Requires-Dist: joblib (>=1.1.0,<2.0.0)
Requires-Dist: nmslib (>=2.0.4,<3.0.0)
Requires-Dist: numpy (>=1.19.5,<2.0.0)
Requires-Dist: pandas (>=0.25.3,<2.0.0)
Requires-Dist: pyspark (>=3.2,<4.0)
Requires-Dist: scikit-learn (>=1.0.2,<2.0.0)
Requires-Dist: scipy (>=1.6.3,<2.0.0)
Requires-Dist: tqdm (>=4.27.0,<5.0.0)
Project-URL: Documentation, https://ambrosia.readthedocs.io
Project-URL: Repository, https://github.com/MobileTeleSystems/Ambrosia
